LICENSE
MANIFEST.in
README.rst
pyproject.toml
setup.cfg
setup.py
oc_python_sdk/__init__.py
oc_python_sdk.egg-info/PKG-INFO
oc_python_sdk.egg-info/SOURCES.txt
oc_python_sdk.egg-info/dependency_links.txt
oc_python_sdk.egg-info/requires.txt
oc_python_sdk.egg-info/top_level.txt
oc_python_sdk/models/application.py
oc_python_sdk/models/payment.py
oc_python_sdk/utils/logger.py
tests/__init__.py
tests/_helpers.py
tests/test_application.py
tests/test_payment.py