Metadata-Version: 2.4
Name: oc_python_sdk
Version: 4.0.0
Summary: Python SDK
Home-page: https://gitlab.com/opencity-labs/area-personale/python_sdk
Author: Opencontent
Author-email: emily.lancietti@opencontent.it
License: GNU GPLv3 License
Classifier: Environment :: Web Environment
Classifier: Intended Audience :: Developers
Classifier: License :: OSI Approved :: GNU General Public License v3 (GPLv3)
Classifier: Operating System :: OS Independent
Classifier: Programming Language :: Python
Classifier: Programming Language :: Python :: 3.8
Classifier: Programming Language :: Python :: 3.9
Classifier: Programming Language :: Python :: 3.10
Requires-Python: >=3.8
License-File: LICENSE
Requires-Dist: pydantic<3.0,>=2.0
Requires-Dist: python-dateutil~=2.8.2
Requires-Dist: python-dotenv~=0.20.0
Dynamic: author
Dynamic: author-email
Dynamic: classifier
Dynamic: description
Dynamic: home-page
Dynamic: license
Dynamic: license-file
Dynamic: requires-dist
Dynamic: requires-python
Dynamic: summary
